pywrithe/__init__.py
pywrithe/writhe.py
pywrithe/writhe_jax.py
PyWrithe-0.0.3.dist-info/LICENSE
PyWrithe-0.0.3.dist-info/METADATA
PyWrithe-0.0.3.dist-info/WHEEL
PyWrithe-0.0.3.dist-info/top_level.txt
PyWrithe-0.0.3.dist-info/RECORD
