Metadata-Version: 2.1
Name: PyWrithe
Version: 0.0.3
Summary: All Python package to compute writhe of closed curves with numpy or jax.numpy
Home-page: https://github.com/RadostW/PyWrithe/
Author: Radost Waszkiewicz
Author-email: radost.waszkiewicz@gmail.com
License: MIT
Project-URL: Documentation, https://pywrithe.readthedocs.io
Project-URL: Source, https://github.com/RadostW/PyWrithe/
Platform: UNKNOWN
License-File: LICENSE
